pandas/__init__.py
pandas/_testing.py
pandas/_typing.py
pandas/_version.py
pandas/conftest.py
pandas/testing.py
pandas/_config/__init__.py
pandas/_config/config.py
pandas/_config/dates.py
pandas/_config/display.py
pandas/_config/localization.py
pandas/_libs/__init__.py
pandas/_libs/algos.cpython-37m-aarch64-linux-gnu.so
pandas/_libs/groupby.cpython-37m-aarch64-linux-gnu.so
pandas/_libs/hashing.cpython-37m-aarch64-linux-gnu.so
pandas/_libs/hashtable.cpython-37m-aarch64-linux-gnu.so
pandas/_libs/index.cpython-37m-aarch64-linux-gnu.so
pandas/_libs/indexing.cpython-37m-aarch64-linux-gnu.so
pandas/_libs/internals.cpython-37m-aarch64-linux-gnu.so
pandas/_libs/interval.cpython-37m-aarch64-linux-gnu.so
pandas/_libs/join.cpython-37m-aarch64-linux-gnu.so
pandas/_libs/json.cpython-37m-aarch64-linux-gnu.so
pandas/_libs/lib.cpython-37m-aarch64-linux-gnu.so
pandas/_libs/missing.cpython-37m-aarch64-linux-gnu.so
pandas/_libs/ops.cpython-37m-aarch64-linux-gnu.so
pandas/_libs/ops_dispatch.cpython-37m-aarch64-linux-gnu.so
pandas/_libs/parsers.cpython-37m-aarch64-linux-gnu.so
pandas/_libs/properties.cpython-37m-aarch64-linux-gnu.so
pandas/_libs/reduction.cpython-37m-aarch64-linux-gnu.so
pandas/_libs/reshape.cpython-37m-aarch64-linux-gnu.so
pandas/_libs/sparse.cpython-37m-aarch64-linux-gnu.so
pandas/_libs/testing.cpython-37m-aarch64-linux-gnu.so
pandas/_libs/tslib.cpython-37m-aarch64-linux-gnu.so
pandas/_libs/writers.cpython-37m-aarch64-linux-gnu.so
pandas/_libs/tslibs/__init__.py
pandas/_libs/tslibs/c_timestamp.cpython-37m-aarch64-linux-gnu.so
pandas/_libs/tslibs/ccalendar.cpython-37m-aarch64-linux-gnu.so
pandas/_libs/tslibs/conversion.cpython-37m-aarch64-linux-gnu.so
pandas/_libs/tslibs/fields.cpython-37m-aarch64-linux-gnu.so
pandas/_libs/tslibs/frequencies.cpython-37m-aarch64-linux-gnu.so
pandas/_libs/tslibs/nattype.cpython-37m-aarch64-linux-gnu.so
pandas/_libs/tslibs/np_datetime.cpython-37m-aarch64-linux-gnu.so
pandas/_libs/tslibs/offsets.cpython-37m-aarch64-linux-gnu.so
pandas_mpmkp-1.0.9.dist-info/AUTHORS.md
pandas_mpmkp-1.0.9.dist-info/LICENSE
pandas_mpmkp-1.0.9.dist-info/METADATA
pandas_mpmkp-1.0.9.dist-info/WHEEL
pandas_mpmkp-1.0.9.dist-info/entry_points.txt
pandas_mpmkp-1.0.9.dist-info/top_level.txt
pandas_mpmkp-1.0.9.dist-info/RECORD
